{
  "BlazeCricket97": {
    "Active": true,
    "RewardType": "Points",
    "RewardValue": 10,
    "MaxUses": 20
  },
  "ShadowViperX": {
    "Active": true,
    "RewardType": "Booth",
    "RewardValue": "UFO_BOOTH",
    "MaxUses": 10
  },
    "GALAXYTOWERV2025": {
    "Active": true,
    "RewardType": "Booth",
    "RewardValue": "B_Galaxy_Redeem",
    "MaxUses": 25
  },
    "SpeedRunnerPLS055": {
    "Active": true,
    "RewardType": "Tool",
    "RewardValue": "Speed",
    "MaxUses": 35
  },
  "EchoWarden64": {
    "Active": false,
    "RewardType": "Points",
    "RewardValue": 50
  },
  "StormTangle9": {
    "Active": true,
    "RewardType": "Booth",
    "RewardValue": "Summer_BOOTH",
    "MaxUses": 15
  },
  "GOLD_HAMMER2025": {
  "Active": true,
  "RewardType": "Tool",
  "RewardValue": "Gold_Hammer",
  "MaxUses": 25
  },
  "TorchPanic37": {
    "Active": true,
    "RewardType": "Points",
    "RewardValue": 25,
    "MaxUses": 10
  }
}
